bulk_keychain/__init__.py
bulk_keychain/__init__.pyi
bulk_keychain/_native.cpython-312-darwin.so
bulk_keychain/py.typed
bulk_keychain-0.1.4.dist-info/METADATA
bulk_keychain-0.1.4.dist-info/WHEEL
bulk_keychain-0.1.4.dist-info/RECORD
