Metadata-Version: 2.4
Name: bulk-keychain
Version: 0.1.4
Classifier: License :: OSI Approved :: MIT License
Classifier: Development Status :: 4 - Beta
Classifier: Intended Audience :: Developers
Classifier: Programming Language :: Python :: 3
Classifier: Programming Language :: Python :: 3.9
Classifier: Programming Language :: Python :: 3.10
Classifier: Programming Language :: Python :: 3.11
Classifier: Programming Language :: Python :: 3.12
Classifier: Programming Language :: Python :: 3.13
Classifier: Programming Language :: Rust
Classifier: Topic :: Security :: Cryptography
Summary: A simple high perf signing lib for BULK txns
Keywords: crypto,signing,ed25519,trading,bulk,dex
License-Expression: MIT
Requires-Python: >=3.9
Project-URL: Repository, https://github.com/bulk-trade/bulk-keychain
